localstack_terraform_init/__init__.py
localstack_terraform_init/extension.py
localstack_terraform_init/packages.py
localstack_extension_terraform_init-0.3.0.dist-info/METADATA
localstack_extension_terraform_init-0.3.0.dist-info/WHEEL
localstack_extension_terraform_init-0.3.0.dist-info/entry_points.txt
localstack_extension_terraform_init-0.3.0.dist-info/top_level.txt
localstack_extension_terraform_init-0.3.0.dist-info/RECORD
