Metadata-Version: 2.4
Name: localstack-extension-terraform-init
Version: 0.3.0
Summary: LocalStack Extension: LocalStack Terraform Init
Home-page: https://github.com/localstack/localstack-extensions/tree/main/terraform-init
Author: Thomas Rausch
Author-email: thomas@localstack.cloud
Requires-Dist: plux
Provides-Extra: dev
Requires-Dist: localstack-core>=3.4; extra == "dev"
